pydantic_rest_client/__init__.py
pydantic_rest_client/aiohttp_rest_client.py
pydantic_rest_client/base_rest_client.py
pydantic_rest_client/exceptions.py
pydantic_rest_client-1.1.0.dist-info/licenses/LICENSE.md
pydantic_rest_client-1.1.0.dist-info/METADATA
pydantic_rest_client-1.1.0.dist-info/WHEEL
pydantic_rest_client-1.1.0.dist-info/top_level.txt
pydantic_rest_client-1.1.0.dist-info/RECORD
