Metadata-Version: 2.4
Name: pydantic-rest-client
Version: 1.1.0
Summary: RESTful client with pydantic validation
Author-email: Damian Sop <damian.sop.official@gmail.com>
License: MIT
Project-URL: Homepage, https://github.com/DamianSop/pydantic_rest_client
Project-URL: Repository, https://github.com/DamianSop/pydantic_rest_client
Project-URL: Issues, https://github.com/DamianSop/pydantic_rest_client/issues
Keywords: rest,api,client,pydantic,validation,async
Classifier: Development Status :: 4 - Beta
Classifier: Intended Audience :: Developers
Classifier: License :: OSI Approved :: MIT License
Classifier: Programming Language :: Python :: 3
Classifier: Programming Language :: Python :: 3.8
Classifier: Programming Language :: Python :: 3.9
Classifier: Programming Language :: Python :: 3.10
Classifier: Programming Language :: Python :: 3.11
Classifier: Programming Language :: Python :: 3.12
Classifier: Topic :: Software Development :: Libraries :: Python Modules
Requires-Python: >=3.8
License-File: LICENSE.md
Requires-Dist: aiohttp>=3.8.0
Requires-Dist: pydantic>=2.0.0
Provides-Extra: dev
Requires-Dist: pytest>=7.0.0; extra == "dev"
Requires-Dist: pytest-asyncio>=0.21.0; extra == "dev"
Requires-Dist: pytest-cov>=4.0.0; extra == "dev"
Requires-Dist: black>=23.0.0; extra == "dev"
Requires-Dist: flake8>=6.0.0; extra == "dev"
Requires-Dist: mypy>=1.0.0; extra == "dev"
Dynamic: license-file
